{
  "title":"35.5 Contact Point of a Wheel Rolling Without Slipping",
  "description": "",
  "file": null,
  "learning_resource_types": ["Lecture Videos"],
  "resource_type": "Video",
  "file_type": "",
  "youtube_key":  "4r1xgrWbALg",
  "captions_file": "/courses/8-01sc-classical-mechanics-fall-2016/5d748292769a58899da4dc6fc4c181c4_4r1xgrWbALg.vtt",
  "transcript_file": "/courses/8-01sc-classical-mechanics-fall-2016/be5ea5c19afff6b54c2cca921babfdbd_4r1xgrWbALg.pdf",
  "thumbnail_file": "https://img.youtube.com/vi/4r1xgrWbALg/default.jpg",
  "archive_url": "https://archive.org/download/MIT8.01F16/MIT8_01F16_L35v05_360p.mp4"}
