{
  "title":"20.3 Work by a Non-Constant Force",
  "description": "",
  "file": null,
  "learning_resource_types": ["Lecture Videos"],
  "resource_type": "Video",
  "file_type": "",
  "youtube_key":  "QAdiRwOLl0A",
  "captions_file": "/courses/8-01sc-classical-mechanics-fall-2016/a46054475d155d3f9e4f0de1db47318e_QAdiRwOLl0A.vtt",
  "transcript_file": "/courses/8-01sc-classical-mechanics-fall-2016/ba2e2e093c521dd5eaa513e85d6bee68_QAdiRwOLl0A.pdf",
  "thumbnail_file": "https://img.youtube.com/vi/QAdiRwOLl0A/default.jpg",
  "archive_url": "https://archive.org/download/MIT8.01F16/MIT8_01F16_L20v03_360p.mp4"}
