{
  "title":"21.2 Scalar Product in Cartesian Coordinates",
  "description": "",
  "file": null,
  "learning_resource_types": ["Lecture Videos"],
  "resource_type": "Video",
  "file_type": "",
  "youtube_key":  "CsHQ35j_1kY",
  "captions_file": "/courses/8-01sc-classical-mechanics-fall-2016/d2e6491bf09c5c15b99504c0460d6c43_CsHQ35j_1kY.vtt",
  "transcript_file": "/courses/8-01sc-classical-mechanics-fall-2016/3891edd63171dec6d589b6586d29e551_CsHQ35j_1kY.pdf",
  "thumbnail_file": "https://img.youtube.com/vi/CsHQ35j_1kY/default.jpg",
  "archive_url": "https://archive.org/download/MIT8.01F16/MIT8_01F16_L21v02_360p.mp4"}
